{
  "channel": "stable",
  "supervisor": "227",
  "homeassistant": {
    "default": "0.110.5",
    "qemux86": "0.110.5",
    "qemux86-64": "0.110.5",
    "qemuarm": "0.110.5",
    "qemuarm-64": "0.110.5",
    "intel-nuc": "0.110.5",
    "raspberrypi": "0.110.5",
    "raspberrypi2": "0.110.5",
    "raspberrypi3": "0.110.5",
    "raspberrypi3-64": "0.110.5",
    "raspberrypi4": "0.110.5",
    "raspberrypi4-64": "0.110.5",
    "tinker": "0.110.5",
    "odroid-c2": "0.110.5",
    "odroid-n2": "0.110.5",
    "odroid-xu": "0.110.5"
  },
  "hassos": {
    "ova": "4.10",
    "rpi": "4.10",
    "rpi0-w": "4.10",
    "rpi2": "4.10",
    "rpi3": "4.10",
    "rpi3-64": "4.10",
    "rpi4": "4.10",
    "rpi4-64": "4.10",
    "tinker": "4.10",
    "odroid-c2": "4.10",
    "odroid-n2": "4.10",
    "odroid-xu4": "4.10",
    "intel-nuc": "4.10"
  },
  "hassos-cli": "19",
  "cli": "25",
  "dns": "9",
  "audio": "14",
  "multicast": "2",
  "image": {
    "core": "homeassistant/{machine}-homeassistant",
    "supervisor": "homeassistant/{arch}-hassio-supervisor",
    "cli": "homeassistant/{arch}-hassio-cli",
    "audio": "homeassistant/{arch}-hassio-audio",
    "dns": "homeassistant/{arch}-hassio-dns",
    "multicast": "homeassistant/{arch}-hassio-multicast"
  }
}
